setup.py
pix/__init__.py
pix_css.egg-info/PKG-INFO
pix_css.egg-info/SOURCES.txt
pix_css.egg-info/dependency_links.txt
pix_css.egg-info/entry_points.txt
pix_css.egg-info/requires.txt
pix_css.egg-info/top_level.txt