Metadata-Version: 1.0
Name: pix-css
Version: 0.1.1
Summary: transform picture to pixel cs
Home-page: UNKNOWN
Author: detailyang
Author-email: detailyang@gmail.com
License: MIT License
Keywords: pixel css art
Platform: any
